{
"type": "FeatureCollection",
"crs": { "type": "name", "properties": { "name": "urn:ogc:def:crs:OGC:1.3:CRS84" } },
                                                                                
"features": [
{ "type": "Feature","id":"1321", "properties": { "name": "居民1","dirtype":"resident" }, "geometry": { "type": "Point", "coordinates": [ 108.849253579389796, 22.643434983778123 ] } },
{ "type": "Feature","id":"1322", "properties": { "name": "组织1","dirtype":"group" }, "geometry": { "type": "Point", "coordinates": [ 108.840218528338056, 22.971115165183342 ] } },
{ "type": "Feature","id":"13231", "properties": { "name": "视频监控点1","status":"on","dirtype":"vedio_monitor" }, "geometry": { "type": "Point", "coordinates": [ 107.792152606335762, 22.649521925935176 ] } },
{ "type": "Feature","id":"13232", "properties": { "name": "视频监控点2","status":"off","dirtype":"vedio_monitor" }, "geometry": { "type": "Point", "coordinates": [ 107.992152606335762, 22.649521925935176 ] } },
{ "type": "Feature","id":"1324", "properties": { "name": "车辆","dirtype":"vehicle" }, "geometry": { "type": "Point", "coordinates": [ 107.801187657387501, 22.977163824275436 ] } },
{ "type": "Feature","id":"1325", "properties": { "name": "建筑物1","dirtype":"building" }, "geometry": { "type": "Point", "coordinates": [ 108.298115465233423, 22.643434983778123 ] } },
{ "type": "Feature","id":"1326", "properties": { "name": "建筑物2","dirtype":"building" }, "geometry": { "type": "Point", "coordinates": [ 108.298115465233423, 22.971115165183342 ] } },
{ "type": "Feature","id":"1327", "properties": { "name": "船","dirtype":"vessels" }, "geometry": { "type": "Point", "coordinates": [ 107.792152606335762, 21.284706278302295 ] } },
{ "type": "Feature","id":"1328", "properties": { "name": "船","dirtype":"vessels" }, "geometry": { "type": "Point", "coordinates": [ 108.849253579389796, 21.278693733790902 ] } },
{ "type": "Feature","id":"1329", "properties": { "name": "船","dirtype":"vessels" }, "geometry": { "type": "Point", "coordinates": [ 108.289080414181669, 21.284706278302295 ] } }
]
}
